certbot_dns_freenom/__init__.py
certbot_dns_freenom/dns_freenom.py
certbot_dns_freenom-1.3.0.dist-info/LICENSE
certbot_dns_freenom-1.3.0.dist-info/METADATA
certbot_dns_freenom-1.3.0.dist-info/WHEEL
certbot_dns_freenom-1.3.0.dist-info/entry_points.txt
certbot_dns_freenom-1.3.0.dist-info/top_level.txt
certbot_dns_freenom-1.3.0.dist-info/RECORD
